[

  {
    "name": "app.org",
    "client_type": "internal",
    "redirect_urls": ["https://app4.com/callback", "https://ahb4.com/callback", "https://ap54.com/callback"],
    "logout_urls": ["https://app4.com/logout"],
    "scopes": ["openid", "email"],
    "branding_settings_path": "branding-settings/app4-branding-setting.json",
    "branding_assets_path": "branding-assets/app4-branding-assets.json",
    "access_token_validity": { "value": 60, "unit": "minutes" },
    "id_token_validity": { "value": 60, "unit": "minutes" },
    "refresh_token_validity": { "value": 8, "unit": "hours" }
  },
  {
    "name": "app1org",
    "client_type": "internal",
    "redirect_urls": ["https://app4.com/callback", "https://ahb4.com/callback", "https://ap54.com/callback"],
    "logout_urls": ["https://app4.com/logout"],
    "scopes": ["openid", "email"],
    "branding_settings_path": "branding-settings/app4-branding-setting.json",
    "branding_assets_path": "branding-assets/app4-branding-assets.json",
    "access_token_validity": { "value": 60, "unit": "minutes" },
    "id_token_validity": { "value": 60, "unit": "minutes" },
    "refresh_token_validity": { "value": 8, "unit": "hours" }
  },
  {
    "name": "ap645org",
    "client_type": "internal",
    "redirect_urls": ["https://app4.com/callback", "https://ahb4.com/callback", "https://ap54.com/callback"],
    "logout_urls": ["https://app4.com/logout"],
    "scopes": ["openid", "email"],
    "branding_settings_path": "branding-settings/app4-branding-setting.json",
    "branding_assets_path": "branding-assets/app4-branding-assets.json",
    "access_token_validity": { "value": 60, "unit": "minutes" },
    "id_token_validity": { "value": 60, "unit": "minutes" },
    "refresh_token_validity": { "value": 8, "unit": "hours" }
  },
  {
    "name": "a545rg",
    "client_type": "internal",
    "redirect_urls": ["https://app4.com/callback", "https://ahb4.com/callback", "https://ap54.com/callback"],
    "logout_urls": ["https://app4.com/logout"],
    "scopes": ["openid", "email"],
    "branding_settings_path": "branding-settings/app4-branding-setting.json",
    "branding_assets_path": "branding-assets/app4-branding-assets.json",
    "access_token_validity": { "value": 60, "unit": "minutes" },
    "id_token_validity": { "value": 60, "unit": "minutes" },
    "refresh_token_validity": { "value": 8, "unit": "hours" }
  },
  {
    "name": "a458972g",
    "client_type": "internal",
    "redirect_urls": ["https://app4.com/callback", "https://ahb4.com/callback", "https://ap54.com/callback"],
    "logout_urls": ["https://app4.com/logout"],
    "scopes": ["openid", "email"],
    "branding_settings_path": "branding-settings/app4-branding-setting.json",
    "branding_assets_path": "branding-assets/app4-branding-assets.json",
    "access_token_validity": { "value": 60, "unit": "minutes" },
    "id_token_validity": { "value": 60, "unit": "minutes" },
    "refresh_token_validity": { "value": 8, "unit": "hours" }
  },
  {
    "name": "a48979rg",
    "client_type": "internal",
    "redirect_urls": ["https://app4.com/callback", "https://ahb4.com/callback", "https://ap54.com/callback"],
    "logout_urls": ["https://app4.com/logout"],
    "scopes": ["openid", "email"],
    "branding_settings_path": "branding-settings/app4-branding-setting.json",
    "branding_assets_path": "branding-assets/app4-branding-assets.json",
    "access_token_validity": { "value": 60, "unit": "minutes" },
    "id_token_validity": { "value": 60, "unit": "minutes" },
    "refresh_token_validity": { "value": 8, "unit": "hours" }
  },
    {
    "name": "jhjucsjuj",
    "client_type": "internal",
    "redirect_urls": ["https://app4.com/callback", "https://ahb4.com/callback", "https://ap54.com/callback"],
    "logout_urls": ["https://app4.com/logout"],
    "scopes": ["openid", "email"],
    "branding_settings_path": "branding-settings/app4-branding-setting.json",
    "branding_assets_path": "branding-assets/app4-branding-assets.json",
    "access_token_validity": { "value": 60, "unit": "minutes" },
    "id_token_validity": { "value": 60, "unit": "minutes" },
    "refresh_token_validity": { "value": 8, "unit": "hours" }
  },
  {
    "name": "jhjsccssujuj",
    "client_type": "internal",
    "redirect_urls": ["https://app4.com/callback", "https://ahb4.com/callback", "https://ap54.com/callback"],
    "logout_urls": ["https://app4.com/logout"],
    "scopes": ["openid", "email"],
    "branding_settings_path": "branding-settings/app4-branding-setting.json",
    "branding_assets_path": "branding-assets/app4-branding-assets.json",
    "access_token_validity": { "value": 60, "unit": "minutes" },
    "id_token_validity": { "value": 60, "unit": "minutes" },
    "refresh_token_validity": { "value": 8, "unit": "hours" }
  },
{
    "name": "jhhhssdffuj",
    "client_type": "internal",
    "redirect_urls": ["https://app4.com/callback", "https://ahb4.com/callback", "https://ap54.com/callback"],
    "logout_urls": ["https://app4.com/logout"],
    "scopes": ["openid", "email"],
    "branding_settings_path": "branding-settings/app4-branding-setting.json",
    "branding_assets_path": "branding-assets/app4-branding-assets.json",
    "access_token_validity": { "value": 60, "unit": "minutes" },
    "id_token_validity": { "value": 60, "unit": "minutes" },
    "refresh_token_validity": { "value": 8, "unit": "hours" }
  },
{
    "name": "jhjuasasjuj",
    "client_type": "internal",
    "redirect_urls": ["https://app4.com/callback", "https://ahb4.com/callback", "https://ap54.com/callback"],
    "logout_urls": ["https://app4.com/logout"],
    "scopes": ["openid", "email"],
    "branding_settings_path": "branding-settings/app4-branding-setting.json",
    "branding_assets_path": "branding-assets/app4-branding-assets.json",
    "access_token_validity": { "value": 60, "unit": "minutes" },
    "id_token_validity": { "value": 60, "unit": "minutes" },
    "refresh_token_validity": { "value": 8, "unit": "hours" }
  },
{
    "name": "jhsddsddvjujuj",
    "client_type": "internal",
    "redirect_urls": ["https://app4.com/callback", "https://ahb4.com/callback", "https://ap54.com/callback"],
    "logout_urls": ["https://app4.com/logout"],
    "scopes": ["openid", "email"],
    "branding_settings_path": "branding-settings/app4-branding-setting.json",
    "branding_assets_path": "branding-assets/app4-branding-assets.json",
    "access_token_validity": { "value": 60, "unit": "minutes" },
    "id_token_validity": { "value": 60, "unit": "minutes" },
    "refresh_token_validity": { "value": 8, "unit": "hours" }
  }
 
 
 
 
 
 
 
]
